ainshamsflow/__init__.py
ainshamsflow/activations.py
ainshamsflow/data.py
ainshamsflow/initializers.py
ainshamsflow/layers.py
ainshamsflow/losses.py
ainshamsflow/metrics.py
ainshamsflow/models.py
ainshamsflow/optimizers.py
ainshamsflow/regularizers.py
ainshamsflow/utils/__init__.py
ainshamsflow/utils/asf_errors.py
ainshamsflow/utils/history.py
ainshamsflow/utils/utils.py
ainshamsflow-0.1.0.dist-info/LICENCE.txt
ainshamsflow-0.1.0.dist-info/METADATA
ainshamsflow-0.1.0.dist-info/WHEEL
ainshamsflow-0.1.0.dist-info/top_level.txt
ainshamsflow-0.1.0.dist-info/RECORD
