Metadata-Version: 2.1
Name: ainshamsflow
Version: 0.1.0
Summary: A keras inspired deep learning framework.
Home-page: https://github.com/PierreNabil/AinShamsFlow
Author: Pierre Nabil
Author-email: pierre.nabil.attya@gmail.com
License: MIT
Keywords: deep learning
Platform: UNKNOWN
Classifier: Development Status :: 3 - Alpha
Classifier: Intended Audience :: Developers
Classifier: Operating System :: OS Independent
Classifier: Topic :: Software Development :: Build Tools
Classifier: License :: OSI Approved :: MIT License
Classifier: Programming Language :: Python :: 3
Requires-Dist: numpy
Requires-Dist: matplotlib
Requires-Dist: varname
